mqt.qfr-1.11.1.dist-info/LICENSE.md
mqt.qfr-1.11.1.dist-info/RECORD
mqt.qfr-1.11.1.dist-info/WHEEL
mqt.qfr-1.11.1.dist-info/top_level.txt
mqt.qfr-1.11.1.dist-info/METADATA
mqt/qfr/pyqfr.pyi
mqt/qfr/CMakeLists.txt
mqt/qfr/__init__.py
mqt/qfr/pyqfr.cpython-39-darwin.so
mqt/qfr/bindings.cpp
mqt/qfr/qiskit/QasmQobjExperiment.hpp
mqt/qfr/qiskit/QuantumCircuit.hpp
