Metadata-Version: 2.1
Name: mqt.qfr
Version: 1.11.1
Summary: A tool for Quantum Functionality Representation
Author-email: Lukas Burgholzer <lukas.burgholzer@jku.at>
License: MIT License
Project-URL: Homepage, https://github.com/cda-tum/qfr
Project-URL: Bug Tracker, https://github.com/cda-tum/qfr/issues
Project-URL: Discussions, https://github.com/cda-tum/qfr/discussions
Keywords: MQT,quantum computing,design automation
Classifier: Development Status :: 5 - Production/Stable
Classifier: Programming Language :: Python :: 3
Classifier: Programming Language :: Python :: 3.7
Classifier: Programming Language :: Python :: 3.8
Classifier: Programming Language :: Python :: 3.9
Classifier: Programming Language :: Python :: 3.10
Classifier: Programming Language :: Python :: 3.11
Classifier: Programming Language :: C++
Classifier: License :: OSI Approved :: MIT License
Classifier: Operating System :: Microsoft :: Windows
Classifier: Operating System :: MacOS
Classifier: Operating System :: POSIX :: Linux
Classifier: Intended Audience :: Science/Research
Classifier: Natural Language :: English
Classifier: Topic :: Scientific/Engineering :: Electronic Design Automation (EDA)
Requires-Python: >=3.7
License-File: LICENSE.md
